codewars_api_py/__init__.py
codewars_api_py/__main__.py
codewars_api_py/api.py
codewars_api_py/cli.py
codewars_api_py/config.py
codewars_api_py/consts.py
codewars_api_py/logs.py
codewars_api_py-1.0.2.dist-info/LICENSE
codewars_api_py-1.0.2.dist-info/METADATA
codewars_api_py-1.0.2.dist-info/WHEEL
codewars_api_py-1.0.2.dist-info/entry_points.txt
codewars_api_py-1.0.2.dist-info/RECORD
