Metadata-Version: 2.1
Name: codewars-api-py
Version: 1.0.2
Summary: Effortlessly interact with Codewars API using a Python wrapper
Home-page: https://github.com/yisuschrist/codewars-api-py
License: GPL-3.0-only
Author: Alejandro González Momblán
Author-email: agelrenorenardo@gmail.com
Requires-Python: >=3.8,<4.0
Classifier: License :: OSI Approved :: GNU General Public License v3 (GPLv3)
Classifier: Programming Language :: Python :: 3
Classifier: Programming Language :: Python :: 3.8
Classifier: Programming Language :: Python :: 3.9
Classifier: Programming Language :: Python :: 3.10
Classifier: Programming Language :: Python :: 3.11
Classifier: Programming Language :: Python :: 3.12
Requires-Dist: platformdirs (>=4.1.0,<5.0.0)
Requires-Dist: requests (>=2.31.0,<3.0.0)
Requires-Dist: rich-argparse-plus (>=0.3.1.4,<0.4.0.0)
Project-URL: Changelog, https://github.com/yisuschrist/codewars-api-py/releases
Project-URL: Issues, https://github.com/yisuschrist/codewars-api-py/issues
Project-URL: Repository, https://github.com/yisuschrist/codewars-api-py
